deepwhisperer/__init__.py
deepwhisperer/_constants.py
deepwhisperer/decorators.py
deepwhisperer/deepwhisperer.py
deepwhisperer-0.1.4.dist-info/LICENSE
deepwhisperer-0.1.4.dist-info/METADATA
deepwhisperer-0.1.4.dist-info/WHEEL
deepwhisperer-0.1.4.dist-info/top_level.txt
deepwhisperer-0.1.4.dist-info/RECORD
