Metadata-Version: 2.2
Name: deepwhisperer
Version: 0.1.4
Summary: A Python package for sending asynchronous Telegram notifications with advanced message handling.
Author-email: Tom Mathews <tom.mathews@nyu.edu>
License: MIT License
Project-URL: Homepage, https://github.com/Mathews-Tom/deepwhisperer
Requires-Python: >=3.12
License-File: LICENSE
Requires-Dist: cachetools>=5.5.0
Requires-Dist: dotenv>=0.9.9
Requires-Dist: httpx>=0.28.0
Requires-Dist: ipykernel>=6.29.5
Requires-Dist: pytest>=8.3.4
Requires-Dist: pytest-mock>=3.14.0
Requires-Dist: twine>=6.1.0
Provides-Extra: dev
Requires-Dist: pytest; extra == "dev"
Requires-Dist: black; extra == "dev"
Requires-Dist: ruff; extra == "dev"
